<?xml version="1.0"?>
<!DOCTYPE hibernate-mapping PUBLIC "-//Hibernate/Hibernate Mapping DTD 3.0//EN"
        "http://hibernate.sourceforge.net/hibernate-mapping-3.0.dtd">

<hibernate-mapping>
    <class name="com.spring.pojo.UserPojo" table="user" catalog="test">
        <id name="id" type="java.lang.Integer">
            <column name="USER_ID" />
            <generator class="increment" />
        </id>
        <property name="name" type="string"/>
        <property name="email" type="string"/>
        <property name="password" type="java.lang.String"></property>
        <property name="address" type="java.lang.String"/>
        <property name="sex" type="java.lang.String"/>
        <property name="country" type="java.lang.String"/>
        <property name="number" type="java.lang.Integer"/>
        </class>
</hibernate-mapping>